bible_reference/BHS.canon
bible_reference/KingJames.canon
bible_reference/LXX.canon
bible_reference/Luther84.names
bible_reference/Luther84_abbr.names
bible_reference/RGG.names
bible_reference/RGG_abbr.names
bible_reference/RGG_lang.names
bible_reference/SBL.names
bible_reference/SBL_abbr.names
bible_reference/SBL_both.info
bible_reference/__init__.py
bible_reference/bible_reference.py
bible_reference/canons.py
bible_reference/default.canon
bible_reference/default.names
bible_reference/empty_first_col.info
bible_reference/infofile.py
bible_reference/internal_booknames.info
bible_reference/luther.canon
bible_reference/naming_schemes.py
bible_reference-1.2.dist-info/LICENSE
bible_reference-1.2.dist-info/METADATA
bible_reference-1.2.dist-info/WHEEL
bible_reference-1.2.dist-info/top_level.txt
bible_reference-1.2.dist-info/RECORD
