Metadata-Version: 2.1
Name: bible_reference
Version: 1.2
Summary: This module implements classes that I have developed to parse and output Bible references.
Home-page: https://github.com/dvorberg/bible_reference
Author: Diedrich Vorberg
Author-email: diedrich@tux4web.de
Classifier: Programming Language :: Python :: 3
Classifier: License :: OSI Approved :: GNU General Public License v2 (GPLv2)
Classifier: Operating System :: OS Independent
Requires-Python: >=3
License-File: LICENSE
